remediate_gcp/__init__.py
remediate_gcp/core.py
remediate_gcp/utils.py
remediate_gcp/runbook/__init__.py
remediate_gcp/runbook/compute_firewall_disable_rule.py
remediate_gcp/runbook/containers_enable_intranode_visibility.py
remediate_gcp/runbook/remediate_sample.py
remediate_gcp/runbook/sql_enable_auto_backup.py
remediate_gcp/runbook/sql_enable_binary_log_backup.py
remediate_gcp-0.1.2.dist-info/DESCRIPTION.rst
remediate_gcp-0.1.2.dist-info/METADATA
remediate_gcp-0.1.2.dist-info/RECORD
remediate_gcp-0.1.2.dist-info/WHEEL
remediate_gcp-0.1.2.dist-info/metadata.json
remediate_gcp-0.1.2.dist-info/top_level.txt
