Metadata-Version: 2.0
Name: remediate-gcp
Version: 0.1.2
Summary: A collection of runbook to remediate GCP resources
Home-page: https://github.com/PaloAltoNetworks/remediate-gcp
Author: nottony
Author-email: nottony-pypi@yahoo.com
License: MIT
Platform: UNKNOWN
Requires-Python: >=3.3
Requires-Dist: google-api-python-client
Requires-Dist: google-auth
